polars_mcu_toolkit-0.1.0.dist-info/METADATA
polars_mcu_toolkit-0.1.0.dist-info/WHEEL
polars_mcu_toolkit-0.1.0.dist-info/licenses/LICENSE
polars_mcu_toolkit/__init__.py
polars_mcu_toolkit/__pycache__/__init__.cpython-39.pyc
polars_mcu_toolkit/__pycache__/__init__.cpython-310.pyc
polars_mcu_toolkit/typing.py
polars_mcu_toolkit/_internal.abi3.so
polars_mcu_toolkit-0.1.0.dist-info/RECORD
